findprime/__init__.py
findprime-1.0.dist-info/LICENSE
findprime-1.0.dist-info/METADATA
findprime-1.0.dist-info/WHEEL
findprime-1.0.dist-info/top_level.txt
findprime-1.0.dist-info/RECORD
