Metadata-Version: 2.1
Name: findprime
Version: 1.0
Summary: A tool for finding prime numbers.
Home-page: UNKNOWN
Author: Jose Lanzas
Author-email: jose97lf@gmail.com
License: GNU GPLv3
Keywords: pyfinding prime numbers
Platform: UNKNOWN
Classifier: Development Status :: 4 - Beta
Classifier: Intended Audience :: Developers
Classifier: Topic :: Utilities
Classifier: License :: OSI Approved :: MIT License
Classifier: Programming Language :: Python :: 3
Classifier: Operating System :: OS Independent
License-File: LICENSE
